{
    "url": "https://x.com/Cal_HHS/status/2051781257554543091",
    "title": null,
    "post": "As Mental Health Awareness Month begins,\n@\nCAgovernor\nremains committed to transforming behavioral health care.\n\nAcross the state, there are new projects opening & more on the way to help create more beds & treatment to get people the care & support they need.\n#MentalHealthForAll",
    "date posted": "2026-05-05T21:49:06.000Z",
    "date extracted": "2026-06-14T13:53:06.610Z",
    "timezone": "UTC"
}