{
    "url": "https://x.com/NLinUganda/status/2057126476789547316",
    "title": null,
    "post": "Did you know 40% of mental health issues develop before 14y.o.?\n@\nrefugeelawproj\nis addressing mental health under the Securing Refugee Host Relations through Enhanced Protection, incorporating the most vulnerable of all: Forcibly displaced children.\n#MentalHealthAwarenessMonth",
    "date posted": "2026-05-20T15:49:06.000Z",
    "date extracted": "2026-06-14T13:53:07.333Z",
    "timezone": "UTC"
}