{
    "url": "https://www.reddit.com/r/therapists/comments/1m1lpca/need_to_leave_therapy_field_for_my_own_mental/",
    "title": "Need to leave therapy field for my own mental health. Not sure where to go from here?",
    "post": "Hi all! Title says it all. If anyone left therapy for a more corporate setting please let me know. I really just want something with career growth and stability but have no idea where to look. I’m realizing I can’t get what I need in private practice or community agencies. The unpredictable and low salary is just too much for me. I’m also just so sick of feeling taken advantage of in this field. Ugh. Any advice appreciated!\nRead more",
    "date posted": "2025-07-16T19:14:56.498Z",
    "date extracted": "2026-06-12T16:36:59.392Z",
    "timezone": "UTC"
}