{
    "url": "https://www.reddit.com/r/AskWomenOver30/comments/1qpjja8/has_anyone_had_their_partner_go_into_outpatient/",
    "title": "Has anyone had their partner go into outpatient mental health care?",
    "post": "My (35F) husband (M32) has been depressed for many years, and I found out that he was suicidal about a year ago. He’s also been diagnosed with Cannabis Use Disorder. I’ve been begging him to get help for years too, but he rarely takes the initiative and when he does it fizzles out.\nFinally, he got on antidepressants and a counselor whom he’s been consistently going to. Yesterday, he told me he’s been researching outpatient care, and he even told his family, who are very supportive. So I think it will actually happen! He says that a couple places he’s looking at can stay him within a week.\nOn one hand I’m so relieved that he’s willing to do this and looking for real treatment. But then on the other hand, I’m worried he’ll have a bad experience or it will make it even worse.\nI would really appreciate any wisdom, or just experiences good or bad or neutral.\nAnd any advice on how I could handle this, and how I could support him while also taking care of myself, is welcome and appreciated!\nRead more",
    "date posted": "2026-01-28T18:26:08.860Z",
    "date extracted": "2026-06-12T16:36:21.588Z",
    "timezone": "UTC"
}