{
    "url": "https://www.reddit.com/r/socialwork/comments/1hx5hyw/discounts_for_mental_health_professionals/",
    "title": "Discounts for mental health professionals",
    "post": "Kind of a dumb post, but have you ever noticed there are not often discounts at businesses for social workers or mental health professionals in general?\nMy local brewery has a teacher discount. My insurance company gives a discount for teachers too. Around COVID I noticed a lot of discounts for nurses and doctors. I think all of these are deserved for sure, but I also see myself as a “public servant” and one who doesn’t make that much money at that. I think  it’s probably just because people don’t think about the profession much at all or don’t understand the work that goes into it. Idk just something I was thinking about!\nRead more",
    "date posted": "2025-01-09T05:11:43.962Z",
    "date extracted": "2026-06-12T16:36:21.455Z",
    "timezone": "UTC"
}