{
    "url": "https://www.reddit.com/r/BigIsland/comments/1io0d5q/mental_health_services/",
    "title": "Mental Health Services",
    "post": "Aloha!\nI have a very close friend who struggles with their mental health. They moved to Hawaii from the US, have been there for quite some time and love it, however, this person no longer has money and refuses to work. As of late, their mental health is declining rapidly.\nI have tried to help as much as I can from the US but they are living out of their car, struggling on food stamps, and seem to be heading into a rock bottom with their schizophrenia. He will refuse inpatient treatment as a previous hospital stay with psychosis was too traumatizing.\nAre there any good resources I should know of? Any mental health facilities you recommend? Advice? Any type of help is appreciated. I feel clueless and unhelpful here. Thank you 🤍\nRead more",
    "date posted": "2025-02-12T20:07:47.549Z",
    "date extracted": "2026-06-12T16:36:27.196Z",
    "timezone": "UTC"
}